kube_manifest_lint/__init__.py
kube_manifest_lint/__main__.py
kube_manifest_lint/main.py
kube_manifest_lint/schemas/v1.17.0/_definitions.json
kube_manifest_lint/schemas/v1.17.0/affinity-v1.json
kube_manifest_lint/schemas/v1.17.0/affinity.json
kube_manifest_lint/schemas/v1.17.0/aggregationrule-rbac-v1.json
kube_manifest_lint/schemas/v1.17.0/aggregationrule-rbac-v1alpha1.json
kube_manifest_lint/schemas/v1.17.0/aggregationrule-rbac-v1beta1.json
kube_manifest_lint/schemas/v1.17.0/aggregationrule.json
kube_manifest_lint/schemas/v1.17.0/all.json
kube_manifest_lint/schemas/v1.17.0/allowedcsidriver-extensions-v1beta1.json
kube_manifest_lint/schemas/v1.17.0/allowedcsidriver-policy-v1beta1.json
kube_manifest_lint/schemas/v1.17.0/allowedcsidriver.json
kube_manifest_lint/schemas/v1.17.0/allowedflexvolume-extensions-v1beta1.json
kube_manifest_lint/schemas/v1.17.0/allowedflexvolume-policy-v1beta1.json
kube_manifest_lint/schemas/v1.17.0/allowedflexvolume.json
kube_manifest_lint/schemas/v1.17.0/allowedhostpath-extensions-v1beta1.json
kube_manifest_lint/schemas/v1.17.0/allowedhostpath-policy-v1beta1.json
kube_manifest_lint/schemas/v1.17.0/allowedhostpath.json
kube_manifest_lint/schemas/v1.17.0/apigroup-meta-v1.json
kube_manifest_lint/schemas/v1.17.0/apigroup.json
kube_manifest_lint/schemas/v1.17.0/apigrouplist-meta-v1.json
kube_manifest_lint/schemas/v1.17.0/apigrouplist.json
kube_manifest_lint/schemas/v1.17.0/apiresource-meta-v1.json
kube_manifest_lint/schemas/v1.17.0/apiresource.json
kube_manifest_lint/schemas/v1.17.0/apiresourcelist-meta-v1.json
kube_manifest_lint/schemas/v1.17.0/apiresourcelist.json
kube_manifest_lint/schemas/v1.17.0/apiservice-apiregistration-v1.json
kube_manifest_lint/schemas/v1.17.0/apiservice-apiregistration-v1beta1.json
kube_manifest_lint/schemas/v1.17.0/apiservice.json
kube_manifest_lint/schemas/v1.17.0/apiservicecondition-apiregistration-v1.json
kube_manifest_lint/schemas/v1.17.0/apiservicecondition-apiregistration-v1beta1.json
kube_manifest_lint-0.2.0.dist-info/entry_points.txt
kube_manifest_lint-0.2.0.dist-info/WHEEL
kube_manifest_lint-0.2.0.dist-info/METADATA
kube_manifest_lint-0.2.0.dist-info/RECORD
